qwikcrud/__init__.py
qwikcrud/cli.py
qwikcrud/generator.py
qwikcrud/helpers.py
qwikcrud/logger.py
qwikcrud/schemas.py
qwikcrud/settings.py
qwikcrud/prompts/system
qwikcrud/provider/__init__.py
qwikcrud/provider/base.py
qwikcrud/provider/dummy.py
qwikcrud/provider/google.py
qwikcrud/provider/openai.py
qwikcrud/templates/fastapi/README.md.j2
qwikcrud/templates/fastapi/requirements.txt.j2
qwikcrud/templates/fastapi/app/__init__.py.j2
qwikcrud/templates/fastapi/app/admin.py.j2
qwikcrud/templates/fastapi/app/crud.py.j2
qwikcrud/templates/fastapi/app/db.py.j2
qwikcrud/templates/fastapi/app/deps.py.j2
qwikcrud/templates/fastapi/app/enums.py.j2
qwikcrud/templates/fastapi/app/main.py.j2
qwikcrud/templates/fastapi/app/models.py.j2
qwikcrud/templates/fastapi/app/pre_start.py.j2
qwikcrud/templates/fastapi/app/schemas.py.j2
qwikcrud/templates/fastapi/app/settings.py.j2
qwikcrud/templates/fastapi/app/storage.py.j2
qwikcrud/templates/fastapi/app/endpoints/__init__.py.j2
qwikcrud/templates/fastapi/app/endpoints/template.py.j2
qwikcrud/templates/fastapi/static/css/style.css
qwikcrud/templates/fastapi/templates/index.html
qwikcrud-0.0.4.dist-info/METADATA
qwikcrud-0.0.4.dist-info/WHEEL
qwikcrud-0.0.4.dist-info/entry_points.txt
qwikcrud-0.0.4.dist-info/licenses/LICENSE
qwikcrud-0.0.4.dist-info/RECORD
